broker_tui/tui.py
broker_tui-0.1.0.dist-info/METADATA
broker_tui-0.1.0.dist-info/WHEEL
broker_tui-0.1.0.dist-info/entry_points.txt
broker_tui-0.1.0.dist-info/top_level.txt
broker_tui-0.1.0.dist-info/RECORD
