Metadata-Version: 2.1
Name: broker-tui
Version: 0.1.0
Summary: The interactive interface for your Broker installation.
Author-email: Jacob Callahan <jacob.callahan05@gmail.com>
Keywords: broker,textual,tui
Classifier: Development Status :: 3 - Alpha
Classifier: Intended Audience :: Developers
Classifier: Natural Language :: English
Classifier: Programming Language :: Python :: 3
Classifier: Programming Language :: Python :: 3.10
Classifier: Programming Language :: Python :: 3.11
Classifier: Programming Language :: Python :: 3.12
Classifier: Programming Language :: Python :: 3.13
Requires-Python: >=3.10
Requires-Dist: broker>=0.6.2
Requires-Dist: textual[syntax]>=1.0.0
